jsonlutils/__init__.py
jsonlutils/jsonl_converter_utils.py
jsonlutils-0.1.0.dist-info/licenses/LICENSE
jsonlutils-0.1.0.dist-info/METADATA
jsonlutils-0.1.0.dist-info/WHEEL
jsonlutils-0.1.0.dist-info/top_level.txt
jsonlutils-0.1.0.dist-info/RECORD
