Metadata-Version: 2.4
Name: jsonlutils
Version: 0.1.0
Summary: Utilities for working with JSONL and JSON formats
Author-email: dja322 <dannyja0112@gmail.com>
License: MIT
Project-URL: Homepage, https://github.com/dja322/JsonlConverterUtils
Keywords: json,jsonl,converter,utilities
Classifier: Programming Language :: Python :: 3
Classifier: License :: OSI Approved :: MIT License
Classifier: Operating System :: OS Independent
Requires-Python: >=3.8
License-File: LICENSE
Dynamic: license-file
